{
  "schema_id": "trader1.summary.v1",
  "project": "TRADER_1",
  "generated_at_utc": "2026-05-01T12:45:23Z",
  "exchange": "BINANCE",
  "market_type": "SPOT",
  "mode": "LIVE",
  "session_id": "mvp1_binance_live_launcher",
  "engine": {
    "status": "SAFE_MODE",
    "source": "STARTUP_PROBE",
    "freshness_status": "PASS",
    "evidence_id": null,
    "message": "provide missing hard truth and rerun startup probe"
  },
  "startup": {
    "status": "BLOCKED",
    "source": "STARTUP_PROBE",
    "freshness_status": "PASS",
    "evidence_id": null,
    "message": "provide missing hard truth and rerun startup probe"
  },
  "operator_status": {
    "status": "UNTESTED",
    "source": "OPERATOR",
    "freshness_status": "UNTESTED",
    "evidence_id": null,
    "message": "operator surface not implemented in MVP-1 summary shell"
  },
  "connectivity": {
    "status": "PASS",
    "source": "HEARTBEAT",
    "freshness_status": "PASS",
    "evidence_id": null,
    "message": "continue read-only monitoring"
  },
  "caches": {},
  "queues": {},
  "rate_limits": {},
  "resources": {
    "status": "PASS",
    "source": "HEARTBEAT",
    "freshness_status": "PASS",
    "evidence_id": null,
    "message": "continue read-only monitoring"
  },
  "portfolio": {
    "source": "SUMMARY_BUILDER",
    "freshness_status": "UNTESTED",
    "source_snapshot_hash": null,
    "source_runtime_cycle_id": null,
    "source_paper_ledger_head_hash": null,
    "source_snapshot_status": "UNTESTED",
    "source_snapshot_generated_at_utc": null,
    "source_snapshot_age_seconds": null,
    "source_snapshot_stale_after_seconds": 300,
    "source_snapshot_freshness_message": "No verified paper portfolio snapshot loaded",
    "source_balance_kind": null,
    "equity": null,
    "cash_available": null,
    "locked_balance": null,
    "position_market_value": null,
    "open_position_count": 0,
    "realized_pnl": null,
    "unrealized_pnl": null,
    "total_pnl": null,
    "mdd": null,
    "next_action": "Run PAPER with a fresh verified paper portfolio ledger before trusting portfolio values"
  },
  "orders": {
    "source": "SUMMARY_BUILDER",
    "freshness_status": "UNTESTED",
    "open_order_count": 0,
    "pending_confirm_count": 0,
    "reconciliation_age_sec": null
  },
  "watch_universe": [],
  "entry_candidates": [],
  "positions": [],
  "strategies": [],
  "market_context": {
    "source": "SUMMARY_BUILDER",
    "freshness_status": "UNTESTED",
    "regime": null,
    "liquidity_status": null,
    "volatility_status": null
  },
  "action_queue": [],
  "recent_errors": [],
  "recent_no_trade_context": [],
  "recent_entry_context": [],
  "fee_snapshot": null,
  "live_ready": {
    "source": "READINESS_SURFACE",
    "live_order_ready": false,
    "live_order_allowed": false,
    "primary_blocker_code": "BINANCE_ADAPTER_SURFACE_ONLY",
    "primary_blocker_message": "Binance live is visible only as a blocked launcher surface; no Binance live adapter is implemented. FUTURES_USDT_M remains blocked and is not root-launchable in MVP-4.",
    "blocks_live_order": true,
    "evidence_id": null
  },
  "applied_snapshot": {
    "snapshot_id": null,
    "source": "NONE",
    "scope_hash": null,
    "freshness_status": "UNTESTED"
  },
  "final_action": "NO_TRADE",
  "blocking_reason": "BINANCE_ADAPTER_SURFACE_ONLY",
  "next_action": "Binance live is visible only as a blocked launcher surface; no Binance live adapter is implemented. FUTURES_USDT_M remains blocked and is not root-launchable in MVP-4."
}
